{
  "createdAt": "2026-07-03T16:17:21.937Z",
  "script": {
    "id": "i2080",
    "name": "UIController",
    "className": "ModuleScript",
    "path": "StarterPlayer.StarterPlayerScripts.Controllers.UIController"
  },
  "sourceHash": "sha256:30fd9b7bc210b69b0933440c75886071639749eeb5d8259988da5020980755dc",
  "sourceLength": 35464,
  "lineCount": 1050,
  "backupPath": "snapshots\\20260703-121721\\StarterPlayer.StarterPlayerScripts.Controllers.UIController.lua",
  "kind": "blueprint-script-overwrite",
  "summary": "Blueprint overwrite: FEED THE VOID Phase 10 Private Test Freeze Overlay",
  "newSourceHash": "sha256:30fd9b7bc210b69b0933440c75886071639749eeb5d8259988da5020980755dc",
  "diff": {
    "oldLineCount": 1050,
    "newLineCount": 1050,
    "changedLineCount": 0,
    "oldLength": 35464,
    "newLength": 35464
  }
}
